adafruit_msa3xx.py
adafruit_circuitpython_msa301-1.3.11.dist-info/licenses/LICENSE
adafruit_circuitpython_msa301-1.3.11.dist-info/METADATA
adafruit_circuitpython_msa301-1.3.11.dist-info/WHEEL
adafruit_circuitpython_msa301-1.3.11.dist-info/top_level.txt
adafruit_circuitpython_msa301-1.3.11.dist-info/RECORD
